loader/__init__.py
loader/celery.py
loader/dictionary.py
loader/file.py
loader/function.py
loader/test.yml
loader/util/__init__.py
loader/util/context.py
loader-2017.9.10.dist-info/DESCRIPTION.rst
loader-2017.9.10.dist-info/METADATA
loader-2017.9.10.dist-info/RECORD
loader-2017.9.10.dist-info/WHEEL
loader-2017.9.10.dist-info/metadata.json
loader-2017.9.10.dist-info/pbr.json
loader-2017.9.10.dist-info/top_level.txt
